kickstart_mcp/__about__.py
kickstart_mcp/__init__.py
kickstart_mcp/config.py
kickstart_mcp/i18n.py
kickstart_mcp/selector.py
kickstart_mcp/state.py
kickstart_mcp/tutorial_base.py
kickstart_mcp/utils.py
kickstart_mcp/tutorials/credits.py
kickstart_mcp/tutorials/fastmcp_client.py
kickstart_mcp/tutorials/fastmcp_weather.py
kickstart_mcp/tutorials/hello_mcp.py
kickstart_mcp/tutorials/implement_sse.py
kickstart_mcp/tutorials/implement_weather.py
kickstart_mcp/tutorials/make_project.py
kickstart_mcp/tutorials/make_server.py
kickstart_mcp/tutorials/modify_init.py
kickstart_mcp/tutorials/modify_toml.py
kickstart_mcp/tutorials/test_server01.py
data/locales/en/credits.csv
data/locales/en/fastmcp_client.csv
data/locales/en/fastmcp_weather.csv
data/locales/en/hello_mcp.csv
data/locales/en/implement_sse.csv
data/locales/en/implement_weather.csv
data/locales/en/init.csv
data/locales/en/make_project.csv
data/locales/en/make_server.csv
data/locales/en/modify_init.csv
data/locales/en/modify_toml.csv
data/locales/en/test_server01.csv
data/locales/ja/credits.csv
data/locales/ja/fastmcp_client.csv
data/locales/ja/fastmcp_weather.csv
data/locales/ja/hello_mcp.csv
data/locales/ja/implement_sse.csv
data/locales/ja/implement_weather.csv
data/locales/ja/init.csv
data/locales/ja/make_project.csv
data/locales/ja/make_server.csv
data/locales/ja/modify_init.csv
data/locales/ja/modify_toml.csv
data/locales/ja/test_server01.csv
data/locales/ko/credits.csv
data/locales/ko/fastmcp_client.csv
data/locales/ko/fastmcp_weather.csv
data/locales/ko/hello_mcp.csv
data/locales/ko/implement_sse.csv
data/locales/ko/implement_weather.csv
data/locales/ko/init.csv
data/locales/ko/make_project.csv
data/locales/ko/make_server.csv
data/locales/ko/modify_init.csv
data/locales/ko/modify_toml.csv
data/locales/ko/test_server01.csv
data/locales/zh/credits.csv
data/locales/zh/fastmcp_client.csv
data/locales/zh/fastmcp_weather.csv
data/locales/zh/hello_mcp.csv
data/locales/zh/implement_sse.csv
kickstart_mcp-0.1.3.dist-info/METADATA
kickstart_mcp-0.1.3.dist-info/WHEEL
kickstart_mcp-0.1.3.dist-info/entry_points.txt
kickstart_mcp-0.1.3.dist-info/licenses/LICENSE.txt
kickstart_mcp-0.1.3.dist-info/RECORD
