Metadata-Version: 2.4
Name: kickstart-mcp
Version: 0.1.3
Summary: Kickstart-mcp is tutorial for using mcp, making your own mcp server/client. We'll guide you through every step of your MCP journey
Project-URL: Documentation, https://github.com/nolleh/kickstart-mcp#readme
Project-URL: Issues, https://github.com/nolleh/kickstart-mcp/issues
Project-URL: Source, https://github.com/nolleh/kickstart-mcp
Author-email: nolleh <nolleh7707@gmail.com>
License-Expression: MIT
License-File: LICENSE.txt
Classifier: Development Status :: 4 - Beta
Classifier: Programming Language :: Python
Classifier: Programming Language :: Python :: 3.8
Classifier: Programming Language :: Python :: 3.9
Classifier: Programming Language :: Python :: 3.10
Classifier: Programming Language :: Python :: 3.11
Classifier: Programming Language :: Python :: 3.12
Classifier: Programming Language :: Python :: Implementation :: CPython
Classifier: Programming Language :: Python :: Implementation :: PyPy
Requires-Python: >=3.8
Requires-Dist: click
Requires-Dist: colorama
Requires-Dist: dotenv
Requires-Dist: mkdocs
Requires-Dist: pygments
Requires-Dist: pyperclip
Requires-Dist: tomli
Requires-Dist: tomli-w
